vscode_offline/__init__.py
vscode_offline/_version.py
vscode_offline/app.py
vscode_offline/download.py
vscode_offline/install.py
vscode_offline/loggers.py
vscode_offline/py.typed
vscode_offline/utils.py
vscode_offline-0.1.10.dist-info/METADATA
vscode_offline-0.1.10.dist-info/WHEEL
vscode_offline-0.1.10.dist-info/entry_points.txt
vscode_offline-0.1.10.dist-info/licenses/LICENSE
vscode_offline-0.1.10.dist-info/RECORD
